setup.cfg
setup.py
useless_utils/__init__.py
useless_utils/crypto.py
useless_utils/design_pattern.py
useless_utils/math.py
useless_utils/regex.py
useless_utils/utils.py
useless_utils.egg-info/PKG-INFO
useless_utils.egg-info/SOURCES.txt
useless_utils.egg-info/dependency_links.txt
useless_utils.egg-info/entry_points.txt
useless_utils.egg-info/requires.txt
useless_utils.egg-info/top_level.txt
useless_utils.egg-info/zip-safe