Metadata-Version: 1.1
Name: useless-utils
Version: 0.0.1
Summary: useless utils function class generator etc. (using Python3)
Home-page: http://kaka-ace.com
Author: kaka_ace
Author-email: xiang.ace@gmail.com
License: http://opensource.org/licenses/MIT
Keywords: useless utils
Platform: UNKNOWN
Classifier: License :: OSI Approved :: MIT License
Classifier: Programming Language :: Python :: 3.4
Classifier: Programming Language :: Python :: Implementation :: CPython
